agents/__init__.py
agents/coding_agent.py
agents/send_email.py
agents/utils.py
agents/pipelines/__init__.py
agents/pipelines/multi_turn_agent.py
agents/providers/__init__.py
agents/providers/codex.py
agents/providers/gemini.py
agents/providers/glm.py
agents/providers/qwen.py
agents/providers/sonnet.py
path2dream_agents-0.1.9.dist-info/METADATA
path2dream_agents-0.1.9.dist-info/WHEEL
path2dream_agents-0.1.9.dist-info/entry_points.txt
path2dream_agents-0.1.9.dist-info/RECORD
