Metadata-Version: 2.4
Name: path2dream-agents
Version: 0.1.9
Summary: Path2Dream AI agents
Requires-Python: >=3.11
Requires-Dist: pytest>=8.4.2
Requires-Dist: python-dotenv>=1.0.1
